{
  "timestamp": "2025-09-12T03:36:40.358199",
  "aging_analysis": {
    "current_aging_rates": {
      "sequential_write_daily": "+2.45%",
      "random_write_daily": "+3.6%",
      "mixed_write_daily": "+4.05%"
    },
    "aging_type": "Positive Aging (Performance Improvement)",
    "key_mechanisms": [
      "SSD Controller Optimization",
      "Kernel Driver Optimization",
      "Wear Leveling Optimization",
      "I/O Scheduler Optimization",
      "Memory Management Improvement"
    ]
  },
  "model_impact": {
    "without_aging": "12-27% error",
    "with_aging": "6-21% error (improved)",
    "aging_benefit": "Aging-aware prediction more accurate"
  },
  "long_term_outlook": {
    "current_phase": "Positive Aging",
    "transition_point": "3-6 months",
    "transition_cause": "Wear Leveling limits, Fragmentation",
    "future_phase": "Negative Aging (Performance Degradation)"
  },
  "modeling_implications": [
    "Continuous aging rate monitoring required",
    "Time-dependent device envelope needed",
    "Positive-to-negative aging transition modeling",
    "Adaptive performance prediction model required"
  ]
}